tree_sitter_epics_db/__init__.py
tree_sitter_epics_db/__init__.pyi
tree_sitter_epics_db/_binding.abi3.so
tree_sitter_epics_db/binding.c
tree_sitter_epics_db/py.typed
tree_sitter_epics_db/queries/highlights.scm
tree_sitter_epics_db/queries/injections.scm
tree_sitter_epics_db-0.2.0.dist-info/METADATA
tree_sitter_epics_db-0.2.0.dist-info/WHEEL
tree_sitter_epics_db-0.2.0.dist-info/top_level.txt
tree_sitter_epics_db-0.2.0.dist-info/RECORD
tree_sitter_epics_db-0.2.0.dist-info/licenses/LICENSE
