Metadata-Version: 2.4
Name: tree-sitter-epics-db
Version: 0.2.0
Summary: tree-sitter grammar for EPICS' database and database definition files
Author-email: Rémi NICOLE <remi.nicole@cea.fr>
License: MIT
Project-URL: Homepage, https://github.com/tree-sitter-grammars/tree-sitter-epics-db
Keywords: incremental,parsing,tree-sitter,epics
Classifier: Intended Audience :: Developers
Classifier: Topic :: Software Development :: Compilers
Classifier: Topic :: Text Processing :: Linguistic
Classifier: Typing :: Typed
Requires-Python: >=3.10
License-File: LICENSE
Provides-Extra: core
Requires-Dist: tree-sitter~=0.25; extra == "core"
Dynamic: license-file
